python_snippet/__init__.py
python_snippet/download_code.py
python_snippet/get_contents.py
python_snippet/main.py
python_snippet/question.py
python_snippet/search.py
python_snippet/utils.py
python_snippet-0.1.7.dist-info/entry_points.txt
python_snippet-0.1.7.dist-info/WHEEL
python_snippet-0.1.7.dist-info/METADATA
python_snippet-0.1.7.dist-info/RECORD
